markitdown_mcp_advanced/__init__.py
markitdown_mcp_advanced/__main__.py
markitdown_mcp_advanced/config.py
markitdown_mcp_advanced/utils.py
markitdown_mcp_advanced/.claude/settings.local.json
markitdown_mcp_advanced/converters/__init__.py
markitdown_mcp_advanced/converters/csv.py
markitdown_mcp_advanced/converters/docx.py
markitdown_mcp_advanced/converters/html.py
markitdown_mcp_advanced/converters/image.py
markitdown_mcp_advanced/converters/pdf.py
markitdown_mcp_advanced/converters/pptx.py
markitdown_mcp_advanced/converters/xls.py
markitdown_mcp_advanced/converters/xlsx.py
markitdown_mcp_advanced-0.0.1.dist-info/METADATA
markitdown_mcp_advanced-0.0.1.dist-info/WHEEL
markitdown_mcp_advanced-0.0.1.dist-info/entry_points.txt
markitdown_mcp_advanced-0.0.1.dist-info/licenses/LICENSE
markitdown_mcp_advanced-0.0.1.dist-info/RECORD
