Metadata-Version: 2.4
Name: markitdown_mcp_advanced
Version: 0.0.1
Summary: Advanced MarkItDown MCP server with PaddleOCR support for PDF, images, and Office documents
Project-URL: Homepage, https://github.com/DuanYan007/markitdown
Project-URL: Issues, https://github.com/DuanYan007/markitdown/issues
Author-email: DuanYan007 <duanyan2024@gmail.com>
License-Expression: MIT
License-File: LICENSE
Keywords: document-conversion,docx,markitdown,mcp,ocr,pdf,pptx,xlsx
Classifier: Operating System :: OS Independent
Classifier: Programming Language :: Python :: 3
Classifier: Topic :: Software Development :: Libraries :: Python Modules
Classifier: Topic :: Text Processing :: Markup
Requires-Python: >=3.9
Requires-Dist: mcp>=0.1.0
Requires-Dist: requests>=2.31.0
Requires-Dist: starlette>=0.27.0
Requires-Dist: uvicorn[standard]>=0.30.0
Provides-Extra: all
Requires-Dist: xlrd==1.2.0; extra == 'all'
Provides-Extra: xls
Requires-Dist: xlrd==1.2.0; extra == 'xls'
